rocksdbserver/__init__.py
rocksdbserver/rocksdbserver.py
rocksdbserver-0.1.4.dist-info/DESCRIPTION.rst
rocksdbserver-0.1.4.dist-info/METADATA
rocksdbserver-0.1.4.dist-info/RECORD
rocksdbserver-0.1.4.dist-info/WHEEL
rocksdbserver-0.1.4.dist-info/metadata.json
rocksdbserver-0.1.4.dist-info/top_level.txt
