Metadata-Version: 2.0
Name: rocksdbserver
Version: 0.1.4
Summary: RocksDB Server
Home-page: https://github.com/deep-compute/rocksdbserver
Author: Deep Compute, LLC
Author-email: contact@deepcompute.com
License: MIT License
Keywords: rocksdbserver rocksdb
Platform: UNKNOWN
Classifier: Programming Language :: Python :: 2.7
Classifier: Environment :: Console
Classifier: Intended Audience :: Developers
Classifier: License :: OSI Approved :: MIT License
Requires-Dist: cython (>=0.20)
Requires-Dist: decorator
Requires-Dist: decorator
Requires-Dist: funcserver
Requires-Dist: gevent
Requires-Dist: jq
Requires-Dist: msgpack-python
Requires-Dist: pyrocksdb
Requires-Dist: tornado
